data/__init__.py
data/datamanager.py
data/engine.py
data/file.py
data/filecontent.py
data/filecontentcache.py
data/fileset.py
data/session.py
tasks/__init__.py
tasks/booleanparameter.py
tasks/descriptionparameter.py
tasks/filesetparameter.py
tasks/floatingpointparameter.py
tasks/integerparameter.py
tasks/labelparameter.py
tasks/multifilesetparameter.py
tasks/optiongroupparameter.py
tasks/parameter.py
tasks/parametercopier.py
tasks/pathparameter.py
tasks/task.py
tasks/taskruninfodialog.py
tasks/taskwidget.py
tasks/taskwidgetexception.py
tasks/taskwidgetmanager.py
tasks/taskwidgetparameterdialog.py
tasks/textparameter.py
tasks/calculatebodycompositionmetricstask/__init__.py
tasks/calculatebodycompositionmetricstask/calculatebodycompositionmetricstask.py
tasks/calculatebodycompositionmetricstask/calculatebodycompositionmetricstaskwidget.py
tasks/copyfilesettask/__init__.py
tasks/copyfilesettask/copyfilesettask.py
tasks/copyfilesettask/copyfilesettaskwidget.py
tasks/createarchivetask/__init__.py
tasks/createarchivetask/createarchivetask.py
tasks/createarchivetask/createarchivetaskwidget.py
tasks/dummytask/__init__.py
tasks/dummytask/dummytask.py
tasks/dummytask/dummytaskwidget.py
tasks/musclefatsegmentationtask/__init__.py
tasks/musclefatsegmentationtask/musclefatsegmentationtask.py
tasks/musclefatsegmentationtask/musclefatsegmentationtaskwidget.py
mosamatic-0.16.0.dist-info/METADATA
mosamatic-0.16.0.dist-info/WHEEL
mosamatic-0.16.0.dist-info/entry_points.txt
mosamatic-0.16.0.dist-info/top_level.txt
mosamatic-0.16.0.dist-info/RECORD
