Metadata-Version: 2.1
Name: mosamatic
Version: 0.16.0
Summary: Desktop tool for analyzing medical images
Author: Ralph Brecheisen
Author-email: r.brecheisen@maastrichtuniversity.nl
License: MIT license
Keywords: mosamatic
Classifier: Development Status :: 2 - Pre-Alpha
Classifier: Intended Audience :: Developers
Classifier: License :: OSI Approved :: MIT License
Classifier: Natural Language :: English
Classifier: Programming Language :: Python :: 3
Classifier: Programming Language :: Python :: 3.5
Classifier: Programming Language :: Python :: 3.6
Classifier: Programming Language :: Python :: 3.7
Classifier: Programming Language :: Python :: 3.8
Requires-Python: >=3.11
Requires-Dist: numpy
Requires-Dist: pandas
Requires-Dist: pyside6
Requires-Dist: sqlalchemy
Requires-Dist: pendulum
Requires-Dist: pydicom
Requires-Dist: pylibjpeg[all]
Requires-Dist: pyjpegls
Requires-Dist: python-gdcm
Requires-Dist: pytest
Requires-Dist: pytest-qt
Requires-Dist: tensorflow
Requires-Dist: pyinstaller
Requires-Dist: matplotlib
Requires-Dist: twine
